Metadata-Version: 2.1
Name: smartinput
Version: 1.0.8
Summary: Much better implementation of the python input function, with hints and history support.
Home-page: https://github.com/shivamsn97/smartinput
Author: Shivam Saini
Author-email: shivamsn97@gmail.com
License: MIT
Platform: UNKNOWN
Classifier: Programming Language :: Python :: 3
Classifier: Programming Language :: Python :: 3.5
Classifier: Programming Language :: Python :: 3.6
Classifier: Programming Language :: Python :: 3.7
Classifier: Programming Language :: Python :: 3.8
Requires-Python: >=3
